resmem/__init__.py
resmem/model.pt
resmem-1.1.6.dist-info/LICENSE
resmem-1.1.6.dist-info/METADATA
resmem-1.1.6.dist-info/WHEEL
resmem-1.1.6.dist-info/top_level.txt
resmem-1.1.6.dist-info/RECORD
