Metadata-Version: 2.1
Name: resmem
Version: 1.1.6
Summary: A package that wraps the ResMem pytorch model.
Home-page: https://github.com/Brain-Bridge-Lab/resmem
Author: Coën D. Needell
Author-email: coen@needell.co
Classifier: Programming Language :: Python :: 3
Classifier: License :: Other/Proprietary License
Classifier: Operating System :: OS Independent
Requires-Python: >=3.6
License-File: LICENSE
Requires-Dist: torch
Requires-Dist: torchvision
